MANIFEST.in
README.txt
setup.py
src/z3c/__init__.py
src/z3c.pluggabletemplates.egg-info/PKG-INFO
src/z3c.pluggabletemplates.egg-info/SOURCES.txt
src/z3c.pluggabletemplates.egg-info/dependency_links.txt
src/z3c.pluggabletemplates.egg-info/namespace_packages.txt
src/z3c.pluggabletemplates.egg-info/not-zip-safe
src/z3c.pluggabletemplates.egg-info/requires.txt
src/z3c.pluggabletemplates.egg-info/top_level.txt
src/z3c/pluggabletemplates/CHANGES.txt
src/z3c/pluggabletemplates/COPYRIGHT.txt
src/z3c/pluggabletemplates/README.txt
src/z3c/pluggabletemplates/ZopePublicLicense.txt
src/z3c/pluggabletemplates/__init__.py
src/z3c/pluggabletemplates/baseview.py
src/z3c/pluggabletemplates/interfaces.py
src/z3c/pluggabletemplates/meta.zcml
src/z3c/pluggabletemplates/pagetemplate.py
src/z3c/pluggabletemplates/tests.py
src/z3c/pluggabletemplates/z3c.pluggabletemplates-meta.zcml
src/z3c/pluggabletemplates/zcml.py
