Metadata-Version: 1.0
Name: z3c.pluggabletemplates
Version: 0.2
Summary: Allows seperation of view code from skin templates like z3c.viewtemplate, but also allows multiple templates to be plugged into your view code.
Home-page: http://code.google.com/p/pluggabletemplates/
Author: Kevin Smith
Author-email: kevin@mcweekly.com
License: ZPL 2.1
Keywords: zope zope3 template
Platform: UNKNOWN
Classifier: Framework :: Zope3
